bandmap/__init__.py
bandmap/__main__.py
bandmap/lib/__init__.py
bandmap/lib/database.py
bandmap/lib/telnetlib.py
bandmap-23.1.30.dist-info/LICENSE.md
bandmap-23.1.30.dist-info/METADATA
bandmap-23.1.30.dist-info/WHEEL
bandmap-23.1.30.dist-info/entry_points.txt
bandmap-23.1.30.dist-info/top_level.txt
bandmap-23.1.30.dist-info/RECORD
