Metadata-Version: 2.1
Name: bandmap
Version: 23.1.30
Summary: Bandmap accessory for fdlogger and wfdlogger
Author-email: Michael Bridak <michael.bridak@gmail.com>
Project-URL: Homepage, https://github.com/mbridak/bandmap
Project-URL: Bug Tracker, https://github.com/mbridak/bandmap/issues
Classifier: Programming Language :: Python :: 3
Classifier: Development Status :: 5 - Production/Stable
Classifier: License :: OSI Approved :: GNU General Public License v3 (GPLv3)
Classifier: Environment :: Console :: Curses
Classifier: Operating System :: POSIX :: Linux
Classifier: Intended Audience :: End Users/Desktop
Classifier: Natural Language :: English
Classifier: Topic :: Communications :: Ham Radio
Requires-Python: >=3.9
License-File: LICENSE.md
Requires-Dist: Rich
Requires-Dist: bs4
Requires-Dist: lxml
Requires-Dist: requests
